s3transfer-stubs/__init__.pyi
s3transfer-stubs/bandwidth.pyi
s3transfer-stubs/compat.pyi
s3transfer-stubs/constants.pyi
s3transfer-stubs/copies.pyi
s3transfer-stubs/crt.pyi
s3transfer-stubs/delete.pyi
s3transfer-stubs/download.pyi
s3transfer-stubs/exceptions.pyi
s3transfer-stubs/futures.pyi
s3transfer-stubs/manager.pyi
s3transfer-stubs/processpool.pyi
s3transfer-stubs/py.typed
s3transfer-stubs/subscribers.pyi
s3transfer-stubs/tasks.pyi
s3transfer-stubs/upload.pyi
s3transfer-stubs/utils.pyi
types_s3transfer-0.11.5.dist-info/licenses/LICENSE
types_s3transfer-0.11.5.dist-info/METADATA
types_s3transfer-0.11.5.dist-info/WHEEL
types_s3transfer-0.11.5.dist-info/top_level.txt
types_s3transfer-0.11.5.dist-info/RECORD
