Metadata-Version: 2.4
Name: types-s3transfer
Version: 0.11.5
Summary: Type annotations and code completion for s3transfer
Author-email: Vlad Emelianov <vlad.emelianov.nz@gmail.com>
License: MIT License
Project-URL: Homepage, https://github.com/youtype/types-s3transfer
Project-URL: Documentation, https://youtype.github.io/mypy_boto3_builder/
Project-URL: Repository, https://github.com/youtype/types-s3transfer
Project-URL: Changelog, https://github.com/youtype/types-s3transfer/releases
Project-URL: Issues, https://github.com/youtype/types-s3transfer/issues
Keywords: s3transfer,type-annotations,pyright,mypy,boto3
Classifier: Development Status :: 5 - Production/Stable
Classifier: Environment :: Console
Classifier: License :: OSI Approved :: MIT License
Classifier: Natural Language :: English
Classifier: Operating System :: OS Independent
Classifier: Programming Language :: Python :: 3
Classifier: Programming Language :: Python :: 3.8
Classifier: Programming Language :: Python :: 3.9
Classifier: Programming Language :: Python :: 3.10
Classifier: Programming Language :: Python :: 3.11
Classifier: Programming Language :: Python :: 3.12
Classifier: Programming Language :: Python :: 3.13
Classifier: Programming Language :: Python :: 3.14
Classifier: Programming Language :: Python :: 3 :: Only
Classifier: Programming Language :: Python :: Implementation :: CPython
Classifier: Typing :: Stubs Only
Classifier: Topic :: Software Development :: Libraries :: Python Modules
Requires-Python: >=3.8
License-File: LICENSE
Dynamic: license-file
